{
	"format_version": "1.12.0",
	"minecraft:geometry": [
		{
			"description": {
				"identifier": "geometry.rainbow_plant",
				"texture_width": 32,
				"texture_height": 32,
				"visible_bounds_width": 2,
				"visible_bounds_height": 2.5,
				"visible_bounds_offset": [0, 0.75, 0]
			},
			"bones": [
				{
					"name": "bouquet_of_flowers",
					"pivot": [0, 0, 0]
				},
				{
					"name": "glass",
					"parent": "bouquet_of_flowers",
					"pivot": [0, 0, 0],
					"cubes": [
						{"origin": [-1.5, 0, -1.5], "size": [3, 4, 3], "uv": [0, 0]}
					]
				},
				{
					"name": "flowers",
					"parent": "bouquet_of_flowers",
					"pivot": [1.03445, 8.30832, 1.7282],
					"cubes": [
						{"origin": [0.33619, 1.57592, -1.1], "size": [1, 5, 0], "pivot": [1.07336, 7.32143, -1.1], "rotation": [8.76156, 31.42215, 16.46902], "uv": [12, 12]},
						{"origin": [0.72033, 6.33423, -1.1], "size": [1, 2, 0], "pivot": [1.07336, 7.32143, -1.1], "rotation": [21.8469, 24.68065, 43.83539], "uv": [14, 12]},
						{"origin": [2.43989, 6.26901, 0.3678], "size": [1, 1, 1], "inflate": 0.2, "pivot": [2.63989, 6.76901, 0.8678], "rotation": [-17.27437, -2.8448, 80.93221], "uv": [13, 6]},
						{"origin": [0.38816, 5.80611, 0.15789], "size": [1, 2, 0], "pivot": [0.38816, 5.80611, 0.15889], "rotation": [-14.73099, -9.55363, 57.73777], "uv": [14, 10]},
						{"origin": [0.73619, 1.57592, 0.5], "size": [1, 4, 0], "pivot": [1.47336, 7.32143, 0.5], "rotation": [-4.36194, -16.96417, 14.65081], "uv": [2, 14]},
						{"origin": [-2.33257, 2.90967, -1.5891], "size": [1, 4, 0], "pivot": [-1.09208, 6.78626, -1.5891], "rotation": [155.0744, 59.39109, 151.63251], "uv": [0, 14]},
						{"origin": [-2.09004, 6.03919, -1.5891], "size": [1, 2, 0], "pivot": [-1.09208, 6.78626, -1.5891], "rotation": [121.97516, 29.31259, 106.99445], "uv": [14, 8]},
						{"origin": [-2.45997, 7.6851, -2.0891], "size": [1, 1, 1], "inflate": 0.2, "pivot": [-1.09208, 6.78626, -1.5891], "rotation": [117.82534, 8.4183, 94.41848], "uv": [13, 0]},
						{"origin": [-2.42534, 8.29296, 1.53745], "size": [1, 1, 1], "inflate": 0.2, "pivot": [-1.82534, 8.79296, 2.03745], "rotation": [-128.02647, 1.96979, 88.46024], "uv": [10, 7]},
						{"origin": [-2.19216, 7.0986, 1.22962], "size": [1, 2, 0], "pivot": [-1.19419, 7.84567, 1.22962], "rotation": [-133.13475, -25.78098, 112.17077], "uv": [4, 14]},
						{"origin": [-2.73257, 2.90967, 1.6109], "size": [1, 5, 0], "pivot": [-1.49208, 9.78626, 1.6109], "rotation": [-162.79508, -49.87173, 157.95324], "uv": [10, 12]},
						{"origin": [-0.63652, 5.98175, -1.1], "size": [2, 1, 0], "pivot": [1.07336, 7.32143, -1.1], "rotation": [30.56955, 11.61158, 71.18334], "uv": [14, 2]},
						{"origin": [-0.27967, 8.33423, -1.1], "size": [3, 3, 0], "pivot": [1.07336, 7.32143, -1.1], "rotation": [21.8469, 24.68065, 43.83539], "uv": [0, 11]},
						{"origin": [-3.02888, 7.23239, 0.05585], "size": [3, 3, 0], "pivot": [-1.86545, 6.04757, 0.05585], "rotation": [6.01178, -7.36941, -48.38751], "uv": [8, 9]},
						{"origin": [-2.02888, 5.23239, 0.05585], "size": [1, 2, 0], "pivot": [-1.86545, 6.04757, 0.05585], "rotation": [6.01178, -7.36941, -48.38751], "uv": [14, 3]},
						{"origin": [-1.76275, 0.66231, 0.05585], "size": [1, 5, 0], "pivot": [-1.86545, 6.04757, 0.05585], "rotation": [2.31829, -9.21531, -23.18686], "uv": [8, 12]},
						{"origin": [-0.22059, 1.6624, 1.12784], "size": [1, 5, 0], "pivot": [-0.32328, 7.04766, 1.12784], "rotation": [-28.6499, 72.74135, -24.36927], "uv": [12, 2]},
						{"origin": [-1.0455, 6.80181, 0.02025], "size": [1, 2, 0], "pivot": [-0.0455, 6.80181, 0.02025], "rotation": [-71.44927, 35.07758, -73.67944], "uv": [0, 7]},
						{"origin": [-1.5455, 8.80181, -0.97975], "size": [2, 0, 2], "pivot": [-0.0455, 6.80181, 0.02025], "rotation": [-71.44927, 35.07758, -73.67944], "uv": [4, 7]},
						{"origin": [0.57489, 9.77973, 0.72854], "size": [2, 0, 2], "pivot": [1.03445, 8.30832, 1.7282], "rotation": [-118.22586, 28.41068, -106.25832], "uv": [7, 0]},
						{"origin": [1.07489, 7.77973, 1.72854], "size": [1, 2, 0], "pivot": [1.03445, 8.30832, 1.7282], "rotation": [-118.22586, 28.41068, -106.25832], "uv": [0, 0]},
						{"origin": [1.14392, 2.67025, 1.72754], "size": [1, 6, 0], "pivot": [1.03445, 8.30832, 1.7282], "rotation": [-153.04389, 62.18031, -152.03185], "uv": [6, 11]}
					]
				},
				{
					"name": "water",
					"parent": "bouquet_of_flowers",
					"pivot": [0, 0, 0],
					"cubes": [
						{"origin": [-1, 0.4, -1], "size": [2, 2, 2], "inflate": 0.1, "uv": [0, 7]}
					]
				}
			]
		}
	]
}