{
  "format_version": "1.16.0",
  "minecraft:entity": {
    "description": {
      "identifier": "custom:display_mars_purple_armoire",
      "is_spawnable": true,
      "is_summonable": true,
      "spawn_egg": true,
      "is_experimental": false
    },
    "component_groups": {},
    "components": {
      "minecraft:damage_sensor": {
        "triggers":[
          { "cause": "all", "deals_damage": false }
        ]
      },
      "minecraft:inventory": {
        "container_type": "inventory",
        "inventory_size": 27
      },
      "minecraft:type_family": { "family": [ "display", "display_mars_purple" ] },
      "minecraft:scale": { "value": 1 },
      "minecraft:collision_box": {
        "width": 1.0,
        "height": 3.03125
      },
      "minecraft:breathable": {
        "breathes_solids": true,
        "breathes_lava": true,
        "breathes_water": true,
        "breathes_air": true
      }
    },
    "events": {
    }
  }
}