{
	"format_version": "1.12.0",
	"minecraft:geometry": [
		{
			"description": {
				"identifier": "geometry.luxury_orchid",
				"texture_width": 64,
				"texture_height": 64,
				"visible_bounds_width": 2,
				"visible_bounds_height": 2.5,
				"visible_bounds_offset": [0, 0.75, 0]
			},
			"bones": [
				{
					"name": "orchid",
					"pivot": [0, -2, 0],
					"cubes": [
						{"origin": [-3, 0, -1.75], "size": [6, 1, 3.5], "uv": [0, 24]},
						{"origin": [-3, 0, -1.75], "size": [6, 1, 3.5], "pivot": [0, 3.18451, 0], "rotation": [0, 90, 0], "uv": [15, 21]},
						{"origin": [-3, 0, -1.75], "size": [6, 1, 3.5], "pivot": [0, 3.18451, 0], "rotation": [-180, 45, -180], "uv": [0, 20]},
						{"origin": [-3, 0, -1.75], "size": [6, 1, 3.5], "pivot": [0, 3.18451, 0], "rotation": [-180, -45, -180], "uv": [17, 17]}
					]
				},
				{
					"name": "sides",
					"parent": "orchid",
					"pivot": [3, -2, 0],
					"cubes": [
						{"origin": [-6.23431, -2.20549, -1.75], "size": [7, 1, 3.5], "pivot": [0, 1.18451, 0], "rotation": [135.24614, 5.29571, 95.31847], "uv": [17, 9]},
						{"origin": [-6.23431, -2.20549, -1.75], "size": [7, 1, 3.5], "pivot": [0, 1.18451, 0], "rotation": [90, 7.5, 90], "uv": [17, 5]},
						{"origin": [-0.76569, -2.20549, -1.75], "size": [7, 1, 3.5], "pivot": [0, 1.18451, 0], "rotation": [135.24614, -5.29571, -95.31847], "uv": [17, 1]},
						{"origin": [-12, -2, -1.75], "size": [7, 1, 3.5], "pivot": [-3, -2, 0], "rotation": [0, 0, 82.5], "uv": [0, 16]},
						{"origin": [-0.76569, -2.20549, -1.75], "size": [7, 1, 3.5], "pivot": [0, 1.18451, 0], "rotation": [-135.24614, 5.29571, -95.31847], "uv": [0, 12]},
						{"origin": [-0.76569, -2.20549, -1.75], "size": [7, 1, 3.5], "pivot": [0, 1.18451, 0], "rotation": [-90, 7.5, -90], "uv": [0, 8]},
						{"origin": [-6.23431, -2.20549, -1.75], "size": [7, 1, 3.5], "pivot": [0, 1.18451, 0], "rotation": [-135.24614, -5.29571, 95.31847], "uv": [0, 4]},
						{"origin": [5, -2, -1.75], "size": [7, 1, 3.5], "pivot": [3, -2, 0], "rotation": [0, 0, -82.5], "uv": [0, 0]}
					]
				},
				{
					"name": "dirt",
					"parent": "orchid",
					"pivot": [2.125, 5.5, -4.5],
					"cubes": [
						{"origin": [-2.625, 5.5, 1.75], "size": [5.25, 1, 1], "uv": [32, 13]},
						{"origin": [-2.125, 5, 2.25], "size": [4.25, 2, 1.5], "inflate": -0.5, "uv": [23, 33]},
						{"origin": [-3.25, 5.5, -1.75], "size": [6.5, 1, 3.5], "uv": [17, 13]},
						{"origin": [-2.625, 5.5, -2.75], "size": [5.25, 1, 1], "uv": [22, 31]},
						{"origin": [-2.125, 5, -3.75], "size": [4.25, 2, 1.5], "inflate": -0.5, "uv": [32, 17]}
					]
				},
				{
					"name": "plant",
					"parent": "orchid",
					"pivot": [0, -2, 0],
					"cubes": [
						{"origin": [-0.75, 9.55411, -0.74407], "size": [1.5, 4, 1.5], "inflate": -0.5, "pivot": [0.5, 10.05411, -0.49407], "rotation": [-12.5, 0, 0], "uv": [34, 37]},
						{"origin": [-0.65, 12.15244, 0.00962], "size": [1.4, 3, 1.4], "inflate": -0.5, "pivot": [0.6, 12.65244, 0.25962], "rotation": [15, 0, 0], "uv": [20, 39]},
						{"origin": [-0.75, 5.5, -0.75], "size": [1.5, 5, 1.5], "inflate": -0.5, "uv": [30, 36]}
					]
				},
				{
					"name": "branch",
					"parent": "plant",
					"pivot": [0.07118, 14.53776, 0.27794],
					"cubes": [
						{"origin": [-0.49966, 13.51907, -0.23151], "size": [1.4, 3.25, 1.4], "inflate": -0.5, "pivot": [0.75034, 14.26907, 0.01849], "rotation": [65, -20, 0], "uv": [16, 39]},
						{"origin": [-0.11425, 13.56621, -1.24056], "size": [2.75, 3.25, 1.001], "inflate": -0.5, "pivot": [0.40034, 15.26907, -0.73151], "rotation": [87.60373, -32.41281, -45.97827], "uv": [36, 28]},
						{"origin": [-1.87336, 13.56621, -1.25545], "size": [2.75, 3.25, 1.001], "inflate": -0.5, "pivot": [0.36205, 15.26907, -0.7464], "rotation": [58.53875, -0.06612, 37.37653], "uv": [24, 36]},
						{"origin": [0.18089, 14.40267, -1.98894], "size": [1.3, 3, 1.3], "inflate": -0.5, "pivot": [1.43089, 15.17767, -1.71394], "rotation": [85, -20, 0], "uv": [12, 39]},
						{"origin": [0.62062, 14.21009, -3.12189], "size": [2.65, 3, 1.001], "inflate": -0.5, "pivot": [1.13089, 15.77767, -2.61394], "rotation": [98.45768, -18.74993, -40.47149], "uv": [36, 8]},
						{"origin": [-0.96605, 14.21009, -3.10526], "size": [2.65, 3, 1.001], "inflate": -0.5, "pivot": [1.17367, 15.77767, -2.59731], "rotation": [71.53118, -14.45841, 39.39968], "uv": [36, 4]},
						{"origin": [0.8228, 14.51962, -3.75256], "size": [1.3, 2.25, 1.3], "inflate": -0.5, "pivot": [2.0728, 15.29462, -3.47756], "rotation": [97.5, -20, 0], "uv": [40, 20]},
						{"origin": [1.35275, 14.10799, -4.96286], "size": [2.6, 4.25, 1.001], "inflate": -0.5, "pivot": [1.8728, 15.69462, -4.47756], "rotation": [110.26537, -4.14658, -59.76562], "uv": [12, 34]},
						{"origin": [-0.31096, 14.10799, -5.00322], "size": [2.6, 4.25, 1.001], "inflate": -0.5, "pivot": [1.769, 15.69462, -4.51792], "rotation": [72.73858, -16.61767, 64.06223], "uv": [6, 34]}
					]
				},
				{
					"name": "branch3",
					"parent": "plant",
					"pivot": [0.07118, 9.88776, -0.02206],
					"rotation": [153.64195, 27.33086, -173.68792],
					"cubes": [
						{"origin": [-0.49966, 8.86907, -0.53151], "size": [1.4, 3.25, 1.4], "inflate": -0.5, "pivot": [0.75034, 9.61907, -0.28151], "rotation": [65, -20, 0], "uv": [8, 39]},
						{"origin": [0.18089, 9.75267, -2.28894], "size": [1.3, 3, 1.3], "inflate": -0.5, "pivot": [1.43089, 10.52767, -2.01394], "rotation": [85, -20, 0], "uv": [4, 39]},
						{"origin": [0.62062, 9.56009, -3.42189], "size": [2.65, 3, 1.001], "inflate": -0.5, "pivot": [1.13089, 11.12767, -2.91394], "rotation": [98.45768, -18.74993, -40.47149], "uv": [18, 35]},
						{"origin": [-0.96605, 9.56009, -3.40526], "size": [2.65, 3, 1.001], "inflate": -0.5, "pivot": [1.17367, 11.12767, -2.89731], "rotation": [71.53118, -14.45841, 39.39968], "uv": [34, 0]},
						{"origin": [0.8228, 9.86962, -4.05256], "size": [1.3, 2.25, 1.3], "inflate": -0.5, "pivot": [2.0728, 10.64462, -3.77756], "rotation": [97.5, -20, 0], "uv": [40, 0]},
						{"origin": [1.35275, 9.45799, -5.26286], "size": [2.6, 4.25, 1.001], "inflate": -0.5, "pivot": [1.8728, 11.04462, -4.77756], "rotation": [110.26537, -4.14658, -59.76562], "uv": [0, 34]},
						{"origin": [-0.31096, 9.45799, -5.30322], "size": [2.6, 4.25, 1.001], "inflate": -0.5, "pivot": [1.769, 11.04462, -4.81792], "rotation": [72.73858, -16.61767, 64.06223], "uv": [33, 32]}
					]
				},
				{
					"name": "branch2",
					"parent": "plant",
					"pivot": [-0.07882, 10.23776, 0.22794],
					"rotation": [-25, -172.5, 0],
					"cubes": [
						{"origin": [-0.65128, 9.46222, -0.27601], "size": [1.4, 3.25, 1.4], "inflate": -0.5, "pivot": [0.59872, 10.21222, -0.02601], "rotation": [65, -20, 0], "uv": [0, 39]},
						{"origin": [0.02928, 10.34582, -2.03344], "size": [1.3, 3, 1.3], "inflate": -0.5, "pivot": [1.27928, 11.12082, -1.75844], "rotation": [85, -20, 0], "uv": [38, 36]},
						{"origin": [0.67118, 10.46276, -3.79706], "size": [1.3, 2.25, 1.3], "inflate": -0.5, "pivot": [1.92118, 11.23776, -3.52206], "rotation": [97.5, -20, 0], "uv": [39, 32]}
					]
				},
				{
					"name": "leaves",
					"parent": "plant",
					"pivot": [0, -2, 0],
					"cubes": [
						{"origin": [-2, 7, -2.25], "size": [4, 1, 2.5], "inflate": -0.5, "pivot": [-0.5, 6.5, -1.25], "rotation": [-20, 0, 0], "uv": [12, 31]},
						{"origin": [-2, 7.1107, -3.37783], "size": [4, 1, 2.5], "inflate": -0.5, "uv": [0, 31]}
					]
				},
				{
					"name": "leaves2",
					"parent": "plant",
					"pivot": [0, 7.25, 0],
					"rotation": [-10, 77.5, 0],
					"cubes": [
						{"origin": [-2, 7.25, -2.25], "size": [4, 1, 2.5], "inflate": -0.5, "pivot": [-0.5, 6.75, -1.25], "rotation": [-20, 0, 0], "uv": [30, 25]},
						{"origin": [-2, 7.3607, -3.37783], "size": [4, 1, 2.5], "inflate": -0.5, "uv": [30, 21]}
					]
				},
				{
					"name": "leaves3",
					"parent": "plant",
					"pivot": [0, 7.25, 0],
					"rotation": [-12.5, 152.5, 0],
					"cubes": [
						{"origin": [-2, 7.25, -2.25], "size": [4, 1, 2.5], "inflate": -0.5, "pivot": [-0.5, 6.75, -1.25], "rotation": [-20, 0, 0], "uv": [24, 28]},
						{"origin": [-2, 7.3607, -3.37783], "size": [4, 1, 2.5], "inflate": -0.5, "uv": [12, 28]}
					]
				},
				{
					"name": "leaves4",
					"parent": "plant",
					"pivot": [0, 6.75, 0],
					"rotation": [-7.5, -107.5, 0],
					"cubes": [
						{"origin": [-2, 6.75, -2.25], "size": [4, 1, 2.5], "inflate": -0.5, "pivot": [-0.5, 6.25, -1.25], "rotation": [-20, 0, 0], "uv": [0, 28]},
						{"origin": [-2, 6.8607, -3.37783], "size": [4, 1, 2.5], "inflate": -0.5, "uv": [18, 25]}
					]
				}
			]
		}
	]
}